discordrpc/__init__.py
discordrpc/baseclient.py
discordrpc/client.py
discordrpc/exceptions.py
discordrpc/payloads.py
discordrpc/response.py
discordrpc/utils.py
DiscordRPC.py-1.0.0.dist-info/LICENSE
DiscordRPC.py-1.0.0.dist-info/METADATA
DiscordRPC.py-1.0.0.dist-info/WHEEL
DiscordRPC.py-1.0.0.dist-info/top_level.txt
DiscordRPC.py-1.0.0.dist-info/zip-safe
DiscordRPC.py-1.0.0.dist-info/RECORD
