Metadata-Version: 2.1
Name: DiscordRPC.py
Version: 1.0.0
Summary: Complete Discord RPC interface written in Python
Home-page: https://github.com/lbots/DiscordRPC.py
Author: LBots
License: MIT
Keywords: discord rich presence discordrpc discordrpc.py rpc api interface richpresence irc
Platform: Windows
Platform: Linux
Platform: OSX
Classifier: Development Status :: 5 - Production/Stable
Classifier: License :: OSI Approved :: MIT License
Classifier: Operating System :: Microsoft :: Windows
Classifier: Operating System :: POSIX :: Linux
Classifier: Operating System :: MacOS :: MacOS X
Classifier: Programming Language :: Python
Classifier: Programming Language :: Python :: 3.5
Classifier: Programming Language :: Python :: 3.6
Classifier: Programming Language :: Python :: 3.7
Classifier: Programming Language :: Python :: 3 :: Only
Classifier: Programming Language :: Python :: Implementation :: CPython
Classifier: Intended Audience :: Developers
Classifier: Topic :: Software Development :: Libraries :: Python Modules
Classifier: Topic :: Software Development :: Libraries
Classifier: Topic :: Communications :: Chat
Classifier: Framework :: AsyncIO
Requires-Python: >=3.5
